main.py
GenomeViewer-0.0.0.dist-info/METADATA
GenomeViewer-0.0.0.dist-info/WHEEL
GenomeViewer-0.0.0.dist-info/top_level.txt
GenomeViewer-0.0.0.dist-info/RECORD
