Metadata-Version: 2.1
Name: GenomeViewer
Version: 0.0.0
Summary: Python Genome Viewer
Author: Li Yao
Requires-Python: >=3.9
